sc_inclusive/__init__.py
sc_inclusive/main.py
sc_inclusive/manifest_utils.py
sc_inclusive/analyzer/__init__.py
sc_inclusive/analyzer/base_analyzer.py
sc_inclusive/analyzer/inclusive_avg_daily_summary_analyzer.py
sc_inclusive/tests/__init__.py
sc_inclusive/tests/sample_config/detail-production.yml
sc_inclusive/tests/sample_config/production.yml
sc_inclusive_analysis-0.0.4.dist-info/LICENSE
sc_inclusive_analysis-0.0.4.dist-info/METADATA
sc_inclusive_analysis-0.0.4.dist-info/WHEEL
sc_inclusive_analysis-0.0.4.dist-info/entry_points.txt
sc_inclusive_analysis-0.0.4.dist-info/top_level.txt
sc_inclusive_analysis-0.0.4.dist-info/RECORD
