Metadata-Version: 2.1
Name: sc-inclusive-analysis
Version: 0.0.4
Summary: python project
Home-page: https://github.com/Scott-Lau/sc-inclusive-analysis
Author: Scott Lau
Author-email: exceedego@126.com
License: MIT
Keywords: python
Platform: POSIX
Classifier: Programming Language :: Python :: 3
Classifier: Programming Language :: Python :: 3.6
Classifier: Programming Language :: Python :: 3.7
Classifier: Programming Language :: Python :: 3.8
Classifier: Programming Language :: Python :: 3.9
Classifier: License :: OSI Approved :: MIT License
Classifier: Operating System :: OS Independent
Classifier: Topic :: Software Development
Classifier: Topic :: Utilities
Requires-Python: >=3.6
License-File: LICENSE
Requires-Dist: sc-utilities (>=0.0.11)
Requires-Dist: sc-config (>=0.0.11)
Requires-Dist: sc-analyzer-base (>=0.0.21)
Requires-Dist: pandas (>=1.3.2)
Requires-Dist: openpyxl (>=3.0.7)
Requires-Dist: xlrd (>=2.0.1)
Requires-Dist: sc-inclusive-balance-detail-analysis (>=0.0.4)
